{
  "layerName": "bhutan_climate_Maximum Temperature_SSP1_2021-2040_mar_may_classified_classified",
  "classifications": [
    {
      "min": -10.245594978333,
      "max": 6.03,
      "color": "#bfd2ff",
      "label": "<= 6.03"
    },
    {
      "min": 6.03,
      "max": 11.89,
      "color": "#ffffbf",
      "label": "6.03 - 11.89"
    },
    {
      "min": 11.89,
      "max": 16.55,
      "color": "#ffd380",
      "label": "11.89 - 16.55"
    },
    {
      "min": 16.55,
      "max": 21.23,
      "color": "#ffaa00",
      "label": "16.55 - 21.23"
    },
    {
      "min": 21.23,
      "max": 33.590934753418,
      "color": "#e60000",
      "label": "> 21.23"
    }
  ],
  "rasterStats": {
    "min": -10.245594978333,
    "max": 33.590934753418,
    "noData": -3.402823e+38
  },
  "created": "2025-11-03T23:53:29.731Z",
  "type": "classified_raster"
}